{
  "fetchedAt": "2026-04-09T22:06:49.850Z",
  "data": {
    "current": {
      "Windows": "version-26c90be22e0d4758",
      "WindowsDate": "4/9/2026, 9:28:28 PM UTC",
      "Mac": "version-cf482a12325c4ed4",
      "MacDate": "4/9/2026, 9:28:34 PM UTC",
      "Android": "2.697.926",
      "AndroidDate": "11/6/2025, 6:42:55 PM UTC",
      "iOS": "2.697.925",
      "iOSDate": "10/30/2025, 4:54:38 PM UTC"
    },
    "future": {
      "Windows": "version-26c90be22e0d4758",
      "WindowsDate": "4/9/2026, 1:02:24 PM UTC",
      "Mac": "version-cf482a12325c4ed4",
      "MacDate": "4/9/2026, 1:01:53 PM UTC"
    },
    "past": {
      "Windows": "version-689e359b09ad43b0",
      "WindowsDate": "4/9/2026, 12:52:40 AM UTC",
      "Mac": "version-08d2b9589bf14135",
      "MacDate": "4/9/2026, 12:40:12 AM UTC"
    }
  }
}
